bacore-0.4.0.dist-info/METADATA
bacore-0.4.0.dist-info/WHEEL
bacore-0.4.0.dist-info/licenses/LICENSE
bacore.libs/libgcc_s-5b5488a6.so.1
bacore/web/__init__.py
bacore/web/main.py
bacore/py.typed
bacore/__init__.py
bacore/config.py
bacore/interfaces/cli_typer.py
bacore/interfaces/cli_git.py
bacore/interfaces/__init__.py
bacore/interfaces/sqlmodel.py
bacore/interfaces/power_point.py
bacore/interfaces/fasthtml/common.py
bacore/interfaces/fasthtml/__init__.py
bacore/interfaces/fasthtml/docs.py
bacore/interfaces/openai.py
bacore/interfaces/dynamics365.py
bacore/domain/testdata.py
bacore/domain/files.py
bacore/domain/source_code.py
bacore/domain/settings.py
bacore/domain/__init__.py
bacore/domain/measurements.py
bacore/domain/errors.py
bacore/domain/system.py
bacore/domain/protocols.py
bacore/domain/responses.py
bacore/interactors/network_handler.py
bacore/interactors/__init__.py
bacore/interactors/os_handler.py
bacore/interactors/file_handler.py
bacore/interactors/source_code_reader.py
bacore/_bacore.abi3.so
bacore-0.4.0.dist-info/RECORD
